{
  "_class": "sharedStyle",
  "do_objectID": "29054F8E-5EC9-45D6-B2F7-CA85966F80A4",
  "name": "button - secondary inverse - center",
  "value": {
    "_class": "style",
    "endMarkerType": 0,
    "miterLimit": 10,
    "sharedObjectID": "29054F8E-5EC9-45D6-B2F7-CA85966F80A4",
    "startMarkerType": 0,
    "textStyle": {
      "_class": "textStyle",
      "encodedAttributes": {
        "MSAttributedStringColorAttribute": {
          "_class": "color",
          "alpha": 1,
          "blue": 0.8,
          "green": 0.8,
          "red": 0.8
        },
        "MSAttributedStringFontAttribute": {
          "_class": "fontDescriptor",
          "attributes": {
            "name": "Roboto-Medium",
            "size": 14
          }
        },
        "MSAttributedStringTextTransformAttribute": 1,
        "paragraphStyle": {
          "_class": "paragraphStyle",
          "alignment": 2
        }
      },
      "verticalAlignment": 0
    },
    "windingRule": 1
  }
}